README.md
setup.py
docums_minify_plugin/__init__.py
docums_minify_plugin/plugin.py
docums_minify_plugin.egg-info/PKG-INFO
docums_minify_plugin.egg-info/SOURCES.txt
docums_minify_plugin.egg-info/dependency_links.txt
docums_minify_plugin.egg-info/entry_points.txt
docums_minify_plugin.egg-info/requires.txt
docums_minify_plugin.egg-info/top_level.txt