Metadata-Version: 1.2
Name: docums-minify-plugin
Version: 0.5.0
Summary: An Docums plugin to minify HTML, JS or CSS files prior to being written to disk
Home-page: https://github.com/khanhduy1407/docums-minify-plugin
Author: NKDuy
Author-email: kn145660@gmail.com
License: MIT
Keywords: docums minify publishing documentation html css
Platform: UNKNOWN
Classifier: Development Status :: 4 - Beta
Classifier: Intended Audience :: Developers
Classifier: Intended Audience :: Information Technology
Classifier: License :: OSI Approved :: MIT License
Classifier: Programming Language :: Python
Classifier: Programming Language :: Python :: 3 :: Only
Classifier: Programming Language :: Python :: 3.4
Classifier: Programming Language :: Python :: 3.5
Classifier: Programming Language :: Python :: 3.6
Classifier: Programming Language :: Python :: 3.7
Requires-Python: >=3.0
